{
  "namesake": {
    "name": "Raj Reddy",
    "imageUrl": "https://avatars.githubusercontent.com/t/8663895?s=116&v=4",
    "materials": [
      {
        "type": "video",
        "url": ""
      }
    ]
  },
  "students": [
    {
        "name": "David Fraser",
        "github": "DavidFra5er",
        "materials": [{
          "type": "cv"
        },
        {
          "type":"video",
          "url": "PWvnWI2N9qk"
        }
      ]        
    },
    {
      "name": "Alessia Finestauri",
      "github": "AleFin95",
      "materials": [
        {
        "type": "cv"
        },
        {
          "type": "video",
          "url": "3KYBWgp8W7Q"
        }
    ]
    },
    {
      "name": "Khider Tariq",
      "github": "khidertar",
      "materials": [
        {
        "type": "cv"
        },
        {
          "type":"video",
          "url":"Wgx649OAVuE"
        }
      ]
    },
    {
      "name": "Joanna Chojnowska",
      "github": "asiek728",
      "materials": [
        {
          "type": "cv"
        },
        {
          "type": "video",
          "url": "pXIgP1lnaEk"
        }
      ]
    },
    {
      "name": "Ashraf Said",
      "github": "nine96as",
      "materials": [
        {
          "type": "cv"
        }
      ]
    },
    {
      "name": "Joel Gooday",
      "github": "jgooday48",
      "materials": [
        {
          "type": "cv"
        },
        {
          "type": "video",
          "url": "ctAtWIcQcIs"
        }
      ]
    },
    {
      "name": "Emma Collins-Opon",
      "github": "ECO786786",
      "materials": [
        {
            "type": "cv"    
        },
        {
          "type":"video",
          "url": "yrm7F8SLnu8"
        }
      ]
    },
    {
      "name": "Billy Scott-Price",
      "github": "Bill2703",
      "materials": [
        {
          "type": "cv"
        },
        {
          "type": "video",
          "url": "Ga6lXrBLtUs"
        }
      ]
    },
    {
      "name": "Sara Madeira",
      "github": "smadeira22",
      "materials": [
        {
        "type": "cv"
        },
        {
          "type": "video",
          "url": "4TsqJ1FPeE8"
        }
    ]
    },
    {
      "name": "Erica Inamura",
      "github": "EricaIna",
      "materials": [
        {
          "type": "cv"
        },
        {
          "type": "video",
          "url": "3KCx1mbwDaQ"
        }
      ]
    },
    {
      "name": "Tahha Butt",
      "github": "tahha00",
      "materials": [
        {
          "type": "cv"
        },
        {
          "type": "video",
          "url": "iSYgAxAXKMY"
        }
      ]
    },
    {
      "name": "Jarvis Ditcher",
      "github": "J-arv1s",
      "materials": [
        {
          "type": "cv"
        },
        {
          "type": "video",
          "url": "CgrRWRRICJc"
        }
      ]
    },
    {
      "name": "Thomas Suggitt",
      "github": "TSuggitt",
      "materials": [
        {
          "type": "cv"
        },
        {
          "type": "video",
          "url": "y63bNcPe7K4"
        }
      ]
    },
    {
      "name": "Booshrat E Sharmin",
      "github": "Booshrat",
      "materials": [
        {
          "type": "cv"
        },
        {
          "type": "video",
          "url": "LSeoRVWoazA"
        }
      ]
    },
    {
      "name": "Alex Warden",
      "github": "AlexWarden2",
      "materials": [
        {
          "type": "cv"
        },
        {
          "type": "video",
          "url": "jW5gzxHwGgY"
        }
      ]
    },
    {
      "name":"Parjal Rai", 
      "github": "pockche123",
      "materials":[
        {
          "type": "cv"
        },
        {
          "type": "video",
          "url":"kp26I-Lkk34"
        }
      ]
    },
    {
      "name": "Esham Younas",
      "github": "Esham156",
      "materials": [
        {
          "type": "cv"
        },
        {
          "type": "video",
          "url": "04Hdmgh8kEM"
        }
      ]
    },
    {
      "name": "Gajani Yoganandan",
      "github": "gajani-yoga",
      "materials": [
        {
          "type": "cv"
        },
        {
          "type": "video",
          "url": "TjKRU0S1XCo"
        }
      ]
    },
    {
      "name":"Tatiana Alchikova", 
      "github": "TatyanaA",
      "materials": [
        {
          "type": "cv"
        }
      ]
    },
    {
      "name": "Stephan Clarke",
      "github": "S-njc"
    },
    { 
      "name": "Joseph Barnett",
      "github": "Joseph-Barnett",
      "materials": [
        {
            "type": "cv"
        },
        {
          "type": "video",
          "url": "Ga32psbGZMo"
      }
    ]
    },
    {
      "name": "Kengi Luca Lambertini",
      "github": "KengiLuca",
      "materials": [
        {
          "type": "cv"
        },
        {
          "type": "video",
          "url": "TWlRmgZdF44"
        }
        
      ]
    },
    {
      "name": "Matthew Bautista Penagos",
      "github": "laplata247",
      "materials": [
        {
          "type": "cv"
        },
        {
          "type": "video",
          "url": "O6KgJDJZAvI"
        }
        
      ]
    }
  ]
}
